gg_start.py
gg_start-0.0.5.dist-info/DESCRIPTION.rst
gg_start-0.0.5.dist-info/METADATA
gg_start-0.0.5.dist-info/RECORD
gg_start-0.0.5.dist-info/WHEEL
gg_start-0.0.5.dist-info/entry_points.txt
gg_start-0.0.5.dist-info/metadata.json
gg_start-0.0.5.dist-info/top_level.txt
