Metadata-Version: 2.0
Name: gg-start
Version: 0.0.5
Summary: Plugin for gg for starting branches
Home-page: https://github.com/peterbe/gg-start
Author: Peter Bengtsson
Author-email: mail@peterbe.com
License: MIT
Platform: UNKNOWN
Requires-Dist: gg
